{
    "packages": [],
    "includes": {
        "include/all$42fa25c3745a65aaaead4dd83f7448ec4f29291d.json": {
            "sha1": "42fa25c3745a65aaaead4dd83f7448ec4f29291d"
        }
    },
    "metadata-url": "/p2/%package%.json",
    "available-packages": [
        "alquemie/advanced-custom-fields-pro",
        "alquemie/alquemie-config",
        "alquemie/cdp-analytics",
        "alquemie/cdp-analytics-gf",
        "alquemie/gf-campaign-fields",
        "alquemie/gf-formname",
        "alquemie/gf-velocify",
        "alquemie/gravityforms",
        "alquemie/gravityformsauthorizenet",
        "alquemie/gravityformsgoogleanalytics",
        "alquemie/gravityformsmailchimp",
        "alquemie/gravityformssignature",
        "alquemie/gravityformsstripe",
        "alquemie/gravityformsuserregistration",
        "alquemie/gravitysmtp",
        "alquemie/repeater2-for-gravity-forms",
        "cedaro/gravity-forms-iframe",
        "roots/bedrock-autoloader",
        "roots/soil"
    ]
}
