{
    "packages": [],
    "includes": {
        "include/all$82f37a0ef0a8aee2bed9dc81113db9d389d239e2.json": {
            "sha1": "82f37a0ef0a8aee2bed9dc81113db9d389d239e2"
        }
    },
    "metadata-url": "/p2/%package%.json",
    "available-packages": [
        "alquemie/advanced-custom-fields-pro",
        "alquemie/alquemie-config",
        "alquemie/gf-campaign-fields",
        "alquemie/gf-formname",
        "alquemie/gf-velocify",
        "alquemie/gravityforms",
        "alquemie/gravityformsmailchimp",
        "alquemie/gravityformssignature",
        "alquemie/gravityformsstripe",
        "alquemie/repeater2-for-gravity-forms",
        "cedaro/gravity-forms-iframe",
        "roots/soil"
    ]
}
